piplinetest/__init__.py
piplinetest/base.py
piplinetest/decorate.py
piplinetest/exceptions.py
piplinetest/http_request.py
piplinetest/import_utils.py
piplinetest/log.py
piplinetest/typing.py
piplinetest-0.8.3.dist-info/METADATA
piplinetest-0.8.3.dist-info/WHEEL
piplinetest-0.8.3.dist-info/RECORD
