Metadata-Version: 2.1
Name: piplinetest
Version: 0.8.3
Summary: 
Author: gui
Author-email: changdi.gui@gmail.com
Requires-Python: >=3.8,<4.0
Classifier: Programming Language :: Python :: 3
Classifier: Programming Language :: Python :: 3.8
Classifier: Programming Language :: Python :: 3.9
Classifier: Programming Language :: Python :: 3.10
Classifier: Programming Language :: Python :: 3.11
Requires-Dist: pydantic (==1.10.12)
Requires-Dist: requests (>=2.31.0,<3.0.0)
